trendfilter/__init__.py
trendfilter/bokeh_theme.py
trendfilter/derivatives.py
trendfilter/extrapolate.py
trendfilter/get_example_data.py
trendfilter/linear_deviations.py
trendfilter/plot_model.py
trendfilter/trendfilter.py
trendfilter-0.3.2.dist-info/LICENSE.txt
trendfilter-0.3.2.dist-info/METADATA
trendfilter-0.3.2.dist-info/WHEEL
trendfilter-0.3.2.dist-info/top_level.txt
trendfilter-0.3.2.dist-info/RECORD
