Metadata-Version: 2.1
Name: trendfilter
Version: 0.3.2
Summary: Useful trendfilter algorithm
Home-page: https://github.com/dave31415/trendfilter
Download-URL: https://pypi.org/project/trendfilter/
Author: David Johnston
Author-email: dave31415@gmail.com
License: MIT
Keywords: cvxpy,trendfilter
License-File: LICENSE.txt
Requires-Dist: pytest
Requires-Dist: cvxpy
Requires-Dist: bokeh
